Metadata-Version: 2.1
Name: iniscrapec
Version: 0.0.4
Summary: Web scraper that take a TAX Code and return the PEC address of the company
Home-page: https://github.com/riccardopaltrinieri/iniscrapec
Author: Riccardo Paltrinieri
Author-email: paltrinieri.rg@gmail.com
License: MIT
Platform: UNKNOWN
Classifier: Programming Language :: Python :: 3
Classifier: License :: OSI Approved :: MIT License
Classifier: Operating System :: OS Independent
Requires-Python: >=3.6
